appel/__init__.py
appel/canvas.py
appel/cli.py
appel/gradescope.py
appel/list_output.py
appel/models.py
appel/policy.py
appel/spreadsheet.py
appel-0.3.0.dist-info/AUTHORS.rst
appel-0.3.0.dist-info/LICENSE
appel-0.3.0.dist-info/METADATA
appel-0.3.0.dist-info/WHEEL
appel-0.3.0.dist-info/entry_points.txt
appel-0.3.0.dist-info/top_level.txt
appel-0.3.0.dist-info/RECORD
