Metadata-Version: 2.1
Name: appel
Version: 0.3.0
Summary: Appel contains tools to process Google Spreadsheets for attendance records and store results on Canvas.
Home-page: https://github.com/zucchini/appel
Author: Cem Gokmen
Author-email: team@zucc.io
License: MIT license
Keywords: appel
Platform: UNKNOWN
Classifier: Development Status :: 2 - Pre-Alpha
Classifier: Intended Audience :: Developers
Classifier: License :: OSI Approved :: MIT License
Classifier: Natural Language :: English
Classifier: Programming Language :: Python :: 2
Classifier: Programming Language :: Python :: 2.7
Classifier: Programming Language :: Python :: 3
Classifier: Programming Language :: Python :: 3.4
Classifier: Programming Language :: Python :: 3.5
Classifier: Programming Language :: Python :: 3.6
Classifier: Programming Language :: Python :: 3.7
Requires-Dist: Click (>=6.0)
Requires-Dist: PyDrive (>=1.3.1)
Requires-Dist: python-dateutil (>=2.7.3)
Requires-Dist: PyYAML (>=4.2b1)
Requires-Dist: requests (>=2.20.0)
Requires-Dist: pytz (>=2018.5)
Requires-Dist: terminaltables (>=3.1.0)
Requires-Dist: six (>=1.12.0)
